README.rst
setup.cfg
setup.py
SpazUtils/__init__.py
SpazUtils/flairRemoval.py
SpazUtils/info.py
SpazUtils/usernotes.py
SpazUtils/utils.py
SpazUtils.egg-info/PKG-INFO
SpazUtils.egg-info/SOURCES.txt
SpazUtils.egg-info/dependency_links.txt
SpazUtils.egg-info/requires.txt
SpazUtils.egg-info/top_level.txt