Metadata-Version: 1.1
Name: SpazUtils
Version: 0.0.7
Summary: Utilities for Automating Moderation on Reddit
Home-page: https://gitlab.jesassn.org/spazbots/SpazUtils
Author: Lil_SpazJoekp
Author-email: lilspazjoekp@gmail.com
License: gpl-3.0
Keywords: spaz utils utilities
Platform: UNKNOWN
Classifier: Development Status :: 3 - Alpha
Classifier: Intended Audience :: Developers
Classifier: License :: OSI Approved :: GNU General Public License v3 (GPLv3)
Classifier: Programming Language :: Python :: 3.6
Classifier: Programming Language :: Python :: 3.7
Classifier: Programming Language :: Python :: 3.8
